ssi_analysis_result_parsers/Ecoli_parser.py
ssi_analysis_result_parsers/Hinfluenzae_parser.py
ssi_analysis_result_parsers/Legionella_parser.py
ssi_analysis_result_parsers/Nmeningitidis_parser.py
ssi_analysis_result_parsers/Spyogenes_parser.py
ssi_analysis_result_parsers/__init__.py
ssi_analysis_result_parsers/_modidx.py
ssi_analysis_result_parsers/blast_parser.py
ssi_analysis_result_parsers/core.py
ssi_analysis_result_parsers/hello_world.py
ssi_analysis_result_parsers/some_string.py
ssi_analysis_result_parsers/config/config.default.env
ssi_analysis_result_parsers/config/config.default.yaml
ssi_analysis_result_parsers-0.0.17.dist-info/licenses/LICENSE
test_input/.DS_Store
test_input/empty_file.txt
test_input/Ecoli/ERR14229029.res
test_input/Ecoli/ERR3528110.res
test_input/Ecoli/samplesheet.tsv
test_input/Hinfluenzae/.DS_Store
test_input/Hinfluenzae/batch_parser_file_paths.tsv
test_input/Hinfluenzae/ariba_ftsI/ftsI_types_table.txt
test_input/Hinfluenzae/ariba_ftsI/sample1.ftsI.ariba.tsv
test_input/Hinfluenzae/ariba_ftsI/sample2.ftsI.ariba.tsv
test_input/Hinfluenzae/biotype/sample1.biotype.blast.tsv
test_input/Hinfluenzae/hicap/sample1.hicap.tsv
test_input/Legionella/batch_parser_file_paths.tsv
test_input/Legionella/lag-1_blast.tsv
test_input/Legionella/lag-1_blast_2.tsv
test_input/Legionella/test.sbt.tsv
test_input/Legionella/test.tsv
test_input/Legionella/test2.sbt.tsv
test_input/Nmeningitidis/batch_parser_file_paths.tsv
test_input/Nmeningitidis/neisseria_mlst_scheme.tsv
test_input/Nmeningitidis/meningotype/meningotype1.tsv
test_input/Nmeningitidis/meningotype/meningotype2.tsv
test_input/Nmeningitidis/meningotype/meningotype3.tsv
test_input/Spyogenes/batch_parser_file_paths.tsv
test_input/Spyogenes/emm_typing/Mga.fasta
test_input/Spyogenes/emm_typing/emm_clusters.txt
test_input/Spyogenes/emm_typing/test1.emm.blast.tsv
test_input/Spyogenes/emm_typing/test1.mga.blast.tsv
test_input/Spyogenes/emm_typing/test2.emm.blast.tsv
test_input/Spyogenes/emm_typing/test2.mga.blast.tsv
test_input/Spyogenes/emm_typing/test3.emm.blast.tsv
ssi_analysis_result_parsers-0.0.17.dist-info/METADATA
ssi_analysis_result_parsers-0.0.17.dist-info/WHEEL
ssi_analysis_result_parsers-0.0.17.dist-info/entry_points.txt
ssi_analysis_result_parsers-0.0.17.dist-info/top_level.txt
ssi_analysis_result_parsers-0.0.17.dist-info/RECORD
